enwiki_offline/__init__.py
enwiki_offline/enwiki_offline_api.py
enwiki_offline/file_io/__init__.py
enwiki_offline-0.2.27.dist-info/METADATA
enwiki_offline-0.2.27.dist-info/WHEEL
enwiki_offline-0.2.27.dist-info/RECORD
